ConsoleColorNew/__init__.py
ConsoleColorNew/main.py
ConsoleColorNew/private.py
consolecolornew-0.0.6.dist-info/METADATA
consolecolornew-0.0.6.dist-info/WHEEL
consolecolornew-0.0.6.dist-info/top_level.txt
consolecolornew-0.0.6.dist-info/RECORD
