Metadata-Version: 2.4
Name: ConsoleColorNew
Version: 0.0.6
Summary: can change color of console output
Home-page: 
Author: buixobra
Author-email: evgenijsattorov@gmail.com
Requires-Python: >=3.10
Requires-Dist: opencv-python>=4.6.0.66
Requires-Dist: numpy>=1.26.3
Requires-Dist: requests>=2.32.2
Requires-Dist: rich>=13.7.1
Dynamic: author
Dynamic: author-email
Dynamic: description
Dynamic: description-content-type
Dynamic: keywords
Dynamic: requires-dist
Dynamic: requires-python
Dynamic: summary
